{
  "formatVersion": 1,
  "nodes": [
    {
      "id": "0",
      "name": "Pulsar",
      "children": [
        {
          "id": "1",
          "name": "effect",
          "children": [],
          "components": [
            {
              "type": "ModelRenderer",
              "config": {
                "modelAssetId": "147",
                "animationId": null,
                "castShadow": false,
                "receiveShadow": false,
                "color": "ffffff",
                "overrideOpacity": false,
                "opacity": null,
                "materialType": "basic",
                "shaderAssetId": null
              },
              "id": "0"
            },
            {
              "type": "Behavior",
              "config": {
                "behaviorName": "ApplyTexture",
                "propertyValues": {
                  "texture": {
                    "type": "string",
                    "value": "res/flames/blue"
                  }
                }
              },
              "id": "1"
            }
          ],
          "position": {
            "x": 0,
            "y": 0.25629740953445435,
            "z": 1.371378779411316
          },
          "orientation": {
            "x": 0,
            "y": 0,
            "z": 0,
            "w": 1
          },
          "scale": {
            "x": 0.5,
            "y": 0.5,
            "z": 0.5
          },
          "visible": true,
          "layer": 0,
          "prefab": null
        }
      ],
      "components": [
        {
          "type": "ModelRenderer",
          "config": {
            "modelAssetId": "136",
            "animationId": null,
            "castShadow": false,
            "receiveShadow": false,
            "color": "ffffff",
            "overrideOpacity": false,
            "opacity": null,
            "materialType": "basic",
            "shaderAssetId": null
          },
          "id": "0"
        },
        {
          "type": "Behavior",
          "config": {
            "behaviorName": "AutoFirearm",
            "propertyValues": {}
          },
          "id": "1"
        }
      ],
      "position": {
        "x": 0,
        "y": 0,
        "z": 0
      },
      "orientation": {
        "x": 0,
        "y": 0,
        "z": 0,
        "w": 1
      },
      "scale": {
        "x": 1,
        "y": 1,
        "z": 1
      },
      "visible": true,
      "layer": 0,
      "prefab": null
    }
  ]
}